{
  "query": "analysis",
  "resolved": "analysis",
  "status": 200,
  "ok": true,
  "data": {
    "id": "analysis",
    "metadata": {
      "operation": "translations",
      "provider": "Oxford University Press",
      "schema": "RetrieveTranslations"
    },
    "results": [
      {
        "id": "analysis",
        "language": "en",
        "lexicalEntries": [
          {
            "entries": [
              {
                "inflections": [
                  {
                    "grammaticalFeatures": [
                      {
                        "id": "plural",
                        "text": "Plural",
                        "type": "Number"
                      }
                    ],
                    "inflectedForm": "analyses",
                    "pronunciations": [
                      {
                        "phoneticNotation": "IPA",
                        "phoneticSpelling": "-siːz"
                      }
                    ]
                  }
                ],
                "pronunciations": [
                  {
                    "audioFile": "https://audio.oxforddictionaries.com/en/mp3/analysis_gb_1_8.mp3",
                    "dialects": [
                      "British English"
                    ],
                    "phoneticNotation": "IPA",
                    "phoneticSpelling": "əˈnalɪsɪs"
                  },
                  {
                    "audioFile": "https://audio.oxforddictionaries.com/en/mp3/analysis_us_1.mp3",
                    "dialects": [
                      "American English"
                    ],
                    "phoneticNotation": "IPA",
                    "phoneticSpelling": "əˈnæləsəs"
                  }
                ],
                "senses": [
                  {
                    "datasetCrossLinks": [
                      {
                        "entry_id": "analysis",
                        "language": "en-gb",
                        "sense_id": "m_en_gbus0030930.010"
                      },
                      {
                        "entry_id": "analysis",
                        "language": "en-gb",
                        "sense_id": "m_en_gbus0030930.016"
                      }
                    ],
                    "examples": [
                      {
                        "text": "in the last analysis",
                        "translations": [
                          {
                            "language": "ru",
                            "text": "в коне́чном счёте"
                          }
                        ]
                      }
                    ],
                    "id": "b-en-ru0000919.002",
                    "translations": [
                      {
                        "language": "ru",
                        "text": "ана́лиз"
                      },
                      {
                        "domains": [
                          {
                            "id": "linguistics",
                            "text": "Linguistics"
                          }
                        ],
                        "language": "ru",
                        "text": "разбо́р"
                      },
                      {
                        "language": "ru",
                        "notes": [
                          {
                            "text": "psychoanalysis",
                            "type": "indicator"
                          }
                        ],
                        "text": "психоана́лиз"
                      }
                    ]
                  }
                ]
              }
            ],
            "language": "en",
            "lexicalCategory": {
              "id": "noun",
              "text": "Noun"
            },
            "text": "analysis"
          }
        ],
        "type": "headword",
        "word": "analysis"
      }
    ],
    "word": "analysis"
  }
}