{
  "query": "and",
  "resolved": "and",
  "status": 200,
  "ok": true,
  "data": {
    "id": "and",
    "metadata": {
      "operation": "translations",
      "provider": "Oxford University Press",
      "schema": "RetrieveTranslations"
    },
    "results": [
      {
        "id": "and",
        "language": "en",
        "lexicalEntries": [
          {
            "entries": [
              {
                "pronunciations": [
                  {
                    "audioFile": "https://audio.oxforddictionaries.com/en/mp3/and_gb_1.mp3",
                    "dialects": [
                      "British English"
                    ],
                    "phoneticNotation": "IPA",
                    "phoneticSpelling": "ənd"
                  },
                  {
                    "audioFile": "https://audio.oxforddictionaries.com/en/mp3/and_gb_3.mp3",
                    "dialects": [
                      "British English"
                    ],
                    "phoneticNotation": "IPA",
                    "phoneticSpelling": "(ə)n"
                  },
                  {
                    "audioFile": "https://audio.oxforddictionaries.com/en/mp3/and_1_gb_1.mp3",
                    "dialects": [
                      "British English"
                    ],
                    "phoneticNotation": "IPA",
                    "phoneticSpelling": "and"
                  },
                  {
                    "audioFile": "https://audio.oxforddictionaries.com/en/mp3/and_us_4.mp3",
                    "dialects": [
                      "American English"
                    ],
                    "phoneticNotation": "IPA",
                    "phoneticSpelling": "ænd"
                  },
                  {
                    "audioFile": "https://audio.oxforddictionaries.com/en/mp3/and_us_3_rr.mp3",
                    "dialects": [
                      "American English"
                    ],
                    "phoneticNotation": "IPA",
                    "phoneticSpelling": "(ə)n"
                  }
                ],
                "senses": [
                  {
                    "datasetCrossLinks": [
                      {
                        "entry_id": "and",
                        "language": "en-gb",
                        "sense_id": "m_en_gbus0031920.013"
                      },
                      {
                        "entry_id": "and",
                        "language": "en-gb",
                        "sense_id": "m_en_gbus0031920.017"
                      },
                      {
                        "entry_id": "and",
                        "language": "en-gb",
                        "sense_id": "m_en_gbus0031920.022"
                      }
                    ],
                    "examples": [
                      {
                        "text": "bread and butter",
                        "translations": [
                          {
                            "language": "ru",
                            "text": "хлеб с ма́слом"
                          }
                        ]
                      },
                      {
                        "text": "the doctor and his wife came",
                        "translations": [
                          {
                            "language": "ru",
                            "text": "пришли́ до́ктор с жено́й"
                          }
                        ]
                      },
                      {
                        "text": "you and I",
                        "translations": [
                          {
                            "language": "ru",
                            "text": "мы с тобо́й/ва́ми"
                          }
                        ]
                      },
                      {
                        "text": "2 and 2 are 4",
                        "translations": [
                          {
                            "language": "ru",
                            "text": "два и/плюс два — четы́ре"
                          }
                        ]
                      },
                      {
                        "notes": [
                          {
                            "text": "to form cpd num, not translated",
                            "type": "indicator"
                          }
                        ],
                        "text": "260",
                        "translations": [
                          {
                            "language": "ru",
                            "text": "две́сти шестьдеся́т"
                          }
                        ]
                      },
                      {
                        "text": "4½",
                        "translations": [
                          {
                            "language": "ru",
                            "text": "четы́ре с полови́ной"
                          }
                        ]
                      }
                    ],
                    "id": "b-en-ru0000947.002",
                    "translations": [
                      {
                        "language": "ru",
                        "notes": [
                          {
                            "text": "connecting words or clauses",
                            "type": "indicator"
                          }
                        ],
                        "text": "и"
                      },
                      {
                        "language": "ru",
                        "notes": [
                          {
                            "text": "in addition",
                            "type": "indicator"
                          }
                        ],
                        "text": "и"
                      },
                      {
                        "language": "ru",
                        "notes": [
                          {
                            "text": "in addition",
                            "type": "indicator"
                          }
                        ],
                        "text": "да"
                      },
                      {
                        "language": "ru",
                        "notes": [
                          {
                            "text": "+ i",
                            "type": "grammaticalNote"
                          },
                          {
                            "text": "with certain closely linked pairs, esp of persons",
                            "type": "indicator"
                          }
                        ],
                        "text": "с"
                      },
                      {
                        "language": "ru",
                        "notes": [
                          {
                            "text": "with nums denoting addition",
                            "type": "indicator"
                          }
                        ],
                        "text": "и"
                      },
                      {
                        "language": "ru",
                        "text": "плюс"
                      },
                      {
                        "language": "ru",
                        "notes": [
                          {
                            "text": "+ i",
                            "type": "grammaticalNote"
                          },
                          {
                            "text": "with following fraction",
                            "type": "indicator"
                          }
                        ],
                        "text": "с"
                      }
                    ]
                  },
                  {
                    "datasetCrossLinks": [
                      {
                        "entry_id": "and",
                        "language": "en-gb",
                        "sense_id": "m_en_gbus0031920.019"
                      },
                      {
                        "entry_id": "and",
                        "language": "en-gb",
                        "sense_id": "m_en_gbus0031920.020"
                      }
                    ],
                    "examples": [
                      {
                        "text": "he ran and ran",
                        "translations": [
                          {
                            "language": "ru",
                            "text": "он всё бежа́л и бежа́л"
                          }
                        ]
                      },
                      {
                        "text": "better and better",
                        "translations": [
                          {
                            "language": "ru",
                            "text": "всё лу́чше (и лу́чше)"
                          }
                        ]
                      },
                      {
                        "text": "they talked for hours and hours",
                        "translations": [
                          {
                            "language": "ru",
                            "text": "они́ разгова́ривали часа́ми"
                          }
                        ]
                      },
                      {
                        "text": "the plain stretched for miles and miles",
                        "translations": [
                          {
                            "language": "ru",
                            "text": "равни́на простира́лась на мно́го миль"
                          }
                        ]
                      }
                    ],
                    "id": "b-en-ru0000947.003",
                    "notes": [
                      {
                        "text": "intensive",
                        "type": "indicator"
                      }
                    ]
                  },
                  {
                    "datasetCrossLinks": [
                      {
                        "entry_id": "and",
                        "language": "en-gb",
                        "sense_id": "m_en_gbus0031920.029"
                      }
                    ],
                    "examples": [
                      {
                        "text": "try and find out",
                        "translations": [
                          {
                            "language": "ru",
                            "text": "постара́йтесь узна́ть"
                          }
                        ]
                      },
                      {
                        "text": "wait and see!",
                        "translations": [
                          {
                            "language": "ru",
                            "text": "погоди́те — ещё уви́дите!"
                          }
                        ]
                      }
                    ],
                    "id": "b-en-ru0000947.004",
                    "notes": [
                      {
                        "text": "in order to",
                        "type": "indicator"
                      },
                      {
                        "text": "not translated before inf",
                        "type": "indicator"
                      }
                    ]
                  },
                  {
                    "datasetCrossLinks": [
                      {
                        "entry_id": "and",
                        "language": "en-gb",
                        "sense_id": "m_en_gbus0031920.018"
                      }
                    ],
                    "examples": [
                      {
                        "text": "move, and I shoot!",
                        "translations": [
                          {
                            "language": "ru",
                            "text": "одно́ движе́ние, и я стреля́ю"
                          }
                        ]
                      }
                    ],
                    "id": "b-en-ru0000947.005",
                    "notes": [
                      {
                        "text": "expressing consequence",
                        "type": "indicator"
                      }
                    ]
                  },
                  {
                    "datasetCrossLinks": [
                      {
                        "entry_id": "and",
                        "language": "en-gb",
                        "sense_id": "m_en_gbus0031920.021"
                      }
                    ],
                    "examples": [
                      {
                        "text": "I shall go, and you stay here",
                        "translations": [
                          {
                            "language": "ru",
                            "text": "я пойду́, а вы остава́йтесь здесь"
                          }
                        ]
                      }
                    ],
                    "id": "b-en-ru0000947.006",
                    "notes": [
                      {
                        "text": "in contrast",
                        "type": "indicator"
                      }
                    ],
                    "translations": [
                      {
                        "language": "ru",
                        "text": "а"
                      }
                    ]
                  },
                  {
                    "datasetCrossLinks": [
                      {
                        "entry_id": "and",
                        "language": "en-gb",
                        "sense_id": "m_en_gbus0031920.019"
                      },
                      {
                        "entry_id": "and",
                        "language": "en-gb",
                        "sense_id": "m_en_gbus0031920.020"
                      }
                    ],
                    "examples": [
                      {
                        "text": "he speaks English, and very well too",
                        "translations": [
                          {
                            "language": "ru",
                            "text": "он говори́т по-англи́йски, и прито́м о́чень хорошо́"
                          }
                        ]
                      }
                    ],
                    "id": "b-en-ru0000947.007",
                    "translations": [
                      {
                        "language": "ru",
                        "notes": [
                          {
                            "text": "emphatic",
                            "type": "indicator"
                          }
                        ],
                        "text": "к тому́ же"
                      },
                      {
                        "language": "ru",
                        "text": "и прито́м"
                      }
                    ]
                  }
                ]
              }
            ],
            "language": "en",
            "lexicalCategory": {
              "id": "conjunction",
              "text": "Conjunction"
            },
            "text": "and"
          }
        ],
        "type": "headword",
        "word": "and"
      }
    ],
    "word": "and"
  }
}