{
  "query": "attractive",
  "resolved": "attractive",
  "status": 200,
  "ok": true,
  "data": {
    "id": "attractive",
    "metadata": {
      "operation": "translations",
      "provider": "Oxford University Press",
      "schema": "RetrieveTranslations"
    },
    "results": [
      {
        "id": "attractive",
        "language": "en",
        "lexicalEntries": [
          {
            "entries": [
              {
                "pronunciations": [
                  {
                    "audioFile": "https://audio.oxforddictionaries.com/en/mp3/attractive_gb_1.mp3",
                    "dialects": [
                      "British English"
                    ],
                    "phoneticNotation": "IPA",
                    "phoneticSpelling": "əˈtraktɪv"
                  },
                  {
                    "audioFile": "https://audio.oxforddictionaries.com/en/mp3/attractive_us_1.mp3",
                    "dialects": [
                      "American English"
                    ],
                    "phoneticNotation": "IPA",
                    "phoneticSpelling": "əˈtræktɪv"
                  }
                ],
                "senses": [
                  {
                    "datasetCrossLinks": [
                      {
                        "entry_id": "attractive",
                        "language": "en-gb",
                        "sense_id": "m_en_gbus0056750.009"
                      }
                    ],
                    "domains": [
                      {
                        "id": "physics",
                        "text": "Physics"
                      }
                    ],
                    "examples": [
                      {
                        "text": "attractive force",
                        "translations": [
                          {
                            "language": "ru",
                            "text": "си́ла притяже́ния"
                          }
                        ]
                      }
                    ],
                    "id": "b-en-ru0001718.002"
                  },
                  {
                    "examples": [
                      {
                        "text": "an attractive dress",
                        "translations": [
                          {
                            "language": "ru",
                            "text": "ми́лое/симпати́чное пла́тье"
                          }
                        ]
                      }
                    ],
                    "id": "b-en-ru0001718.003",
                    "translations": [
                      {
                        "language": "ru",
                        "registers": [
                          {
                            "id": "figurative",
                            "text": "Figurative"
                          }
                        ],
                        "text": "привлека́тельный"
                      },
                      {
                        "language": "ru",
                        "text": "притяга́тельный"
                      }
                    ]
                  }
                ]
              }
            ],
            "language": "en",
            "lexicalCategory": {
              "id": "adjective",
              "text": "Adjective"
            },
            "text": "attractive"
          }
        ],
        "type": "headword",
        "word": "attractive"
      }
    ],
    "word": "attractive"
  }
}